contrastive_inverse_regression/__init__.py
contrastive_inverse_regression/cir.py
contrastive_inverse_regression-1.0.13.dist-info/LICENSE
contrastive_inverse_regression-1.0.13.dist-info/METADATA
contrastive_inverse_regression-1.0.13.dist-info/WHEEL
contrastive_inverse_regression-1.0.13.dist-info/top_level.txt
contrastive_inverse_regression-1.0.13.dist-info/RECORD
