Metadata-Version: 2.1
Name: contrastive-inverse-regression
Version: 1.0.13
Home-page: https://github.com/myueen/contrastive-inverse-regression
Author: Yueen Ma
Author-email: myueen@ad.unc.edu
License: MIT
Requires-Python: >=3.7
License-File: LICENSE
